localstack_openai/__init__.py
localstack_openai/extension.py
localstack_openai/mock_openai.py
localstack_extension_openai-0.1.0.dist-info/LICENSE.txt
localstack_extension_openai-0.1.0.dist-info/METADATA
localstack_extension_openai-0.1.0.dist-info/WHEEL
localstack_extension_openai-0.1.0.dist-info/entry_points.txt
localstack_extension_openai-0.1.0.dist-info/top_level.txt
localstack_extension_openai-0.1.0.dist-info/RECORD
