Metadata-Version: 2.1
Name: localstack-extension-openai
Version: 0.1.0
Summary: LocalStack Extension: OpenAI
Home-page: https://github.com/localstack/localstack-extensions/tree/main/openai
Author: Cristopher Pinzon
Author-email: cristopher.pinzon@localstack.cloud
License: Apache License 2.0
Classifier: Development Status :: 5 - Production/Stable
Classifier: License :: OSI Approved :: Apache Software License
Classifier: Operating System :: OS Independent
Classifier: Programming Language :: Python :: 3
Classifier: Programming Language :: Python :: 3.8
Classifier: Programming Language :: Python :: 3.9
Classifier: Topic :: Software Development :: Libraries
Classifier: Topic :: Utilities
License-File: LICENSE.txt
Requires-Dist: faker >=8.12.1
Requires-Dist: plux >=1.3
Requires-Dist: rolo >=0.3
Provides-Extra: dev
Requires-Dist: localstack-core >=3.1 ; extra == 'dev'
Requires-Dist: openai <1.0,>=0.10.2 ; extra == 'dev'
Requires-Dist: pytest >=6.2.4 ; extra == 'dev'
Requires-Dist: black ==22.3.0 ; extra == 'dev'
Requires-Dist: isort ==5.10.1 ; extra == 'dev'
